{
  "model_name": "XGBoost",
  "model_type": "XGBClassifier",
  "parameters": {
    "objective": "binary:logistic",
    "base_score": null,
    "booster": null,
    "callbacks": null,
    "colsample_bylevel": null,
    "colsample_bynode": null,
    "colsample_bytree": null,
    "device": null,
    "early_stopping_rounds": null,
    "enable_categorical": false,
    "eval_metric": "logloss",
    "feature_types": null,
    "feature_weights": null,
    "gamma": null,
    "grow_policy": null,
    "importance_type": null,
    "interaction_constraints": null,
    "learning_rate": 0.2,
    "max_bin": null,
    "max_cat_threshold": null,
    "max_cat_to_onehot": null,
    "max_delta_step": null,
    "max_depth": null,
    "max_leaves": null,
    "min_child_weight": null,
    "missing": NaN,
    "monotone_constraints": null,
    "multi_strategy": null,
    "n_estimators": 100,
    "n_jobs": null,
    "num_parallel_tree": null,
    "random_state": null,
    "reg_alpha": null,
    "reg_lambda": null,
    "sampling_method": null,
    "scale_pos_weight": null,
    "subsample": null,
    "tree_method": null,
    "validate_parameters": null,
    "verbosity": null
  },
  "performance_metrics": {
    "accuracy": 0.931,
    "precision": 0.925,
    "recall": 0.6981,
    "f1_score": 0.7957,
    "auc_score": 0.9642
  },
  "feature_names": [
    "Age",
    "TypeofContact",
    "CityTier",
    "DurationOfPitch",
    "Occupation",
    "Gender",
    "NumberOfPersonVisiting",
    "NumberOfFollowups",
    "ProductPitched",
    "PreferredPropertyStar",
    "MaritalStatus",
    "NumberOfTrips",
    "Passport",
    "PitchSatisfactionScore",
    "OwnCar",
    "NumberOfChildrenVisiting",
    "Designation",
    "MonthlyIncome"
  ],
  "training_date": "2025-08-31 08:46:54"
}